Metadata-Version: 2.1
Name: mywattsmon
Version: 0.9.5
Summary: Monitoring power and energy in the smart home
Author: https://github.com/berryunit
License: mywattsmon
Project-URL: repository, https://github.com/berryunit/mywattsmon
Keywords: smart home,diy,power,energy
Classifier: Development Status :: 4 - Beta
Classifier: Operating System :: OS Independent
Classifier: License :: OSI Approved :: MIT License
Classifier: Programming Language :: Python :: 3
Requires-Python: >=3.11
License-File: LICENSE
Provides-Extra: device
Requires-Dist: requests ; extra == 'device'
Requires-Dist: fritzconnection ; extra == 'device'
Requires-Dist: minimalmodbus ; extra == 'device'
